LICENSE
MANIFEST.in
README.rst
setup.py
django_random_image.egg-info/PKG-INFO
django_random_image.egg-info/SOURCES.txt
django_random_image.egg-info/dependency_links.txt
django_random_image.egg-info/requires.txt
django_random_image.egg-info/top_level.txt
random_image/__init__.py
random_image/admin.py
random_image/apps.py
random_image/models.py
random_image/tests.py
random_image/migrations/0001_initial.py
random_image/migrations/__init__.py
random_image/templatetags/__init__.py
random_image/templatetags/random_image.py